snapdump/__init__.py
snapdump/cli.py
snapdump-1.0.7.data/scripts/snapdump
snapdump-1.0.7.dist-info/LICENSE
snapdump-1.0.7.dist-info/METADATA
snapdump-1.0.7.dist-info/WHEEL
snapdump-1.0.7.dist-info/top_level.txt
snapdump-1.0.7.dist-info/RECORD
