Metadata-Version: 2.1
Name: snapdump
Version: 1.0.7
Summary: ZFS incremental snapshot dump and restore tool
Home-page: https://github.com/omry/snapdump
Author: Omry Yadan
Author-email: omry@yadan.net
License: UNKNOWN
Keywords: zfs snapshot dump restore backup off-site
Platform: UNKNOWN
Classifier: Programming Language :: Python :: 3
Classifier: License :: OSI Approved :: MIT License
Requires-Dist: omegaconf (>=1.3.0)
Requires-Dist: setuptools
